printmsg4lo2pypi/__init__.py
printmsg4lo2pypi/print_msg_file.py
printmsg4lo2-0.0.1.dist-info/METADATA
printmsg4lo2-0.0.1.dist-info/WHEEL
printmsg4lo2-0.0.1.dist-info/top_level.txt
printmsg4lo2-0.0.1.dist-info/RECORD
